idsim/__init__.py
idsim/detector.py
idsim/loss.py
idsim/core/__init__.py
idsim/core/iresnet.py
idsim/core/iresnet2060.py
idsim/core/mobilefacenet.py
idsim/core/vit.py
idsim-0.0.1.data/data/requirements.txt
tests/__init__.py
tests/test_inference.py
idsim-0.0.1.dist-info/METADATA
idsim-0.0.1.dist-info/WHEEL
idsim-0.0.1.dist-info/top_level.txt
idsim-0.0.1.dist-info/RECORD
