Metadata-Version: 2.1
Name: idsim
Version: 0.0.1
Summary: Face Recognition Metric
Home-page: https://github.com/m-pektas/IdentitySimilarity
Author: Muhammed Pektas
Author-email: mhmdpkts@gmail.com
Classifier: Programming Language :: Python :: 3
Classifier: License :: OSI Approved :: BSD License
Classifier: Operating System :: OS Independent
Requires-Python: >=3.7
Requires-Dist: gdown ==4.7.3
Requires-Dist: torchvision >=0.10.0
Requires-Dist: opencv-python
Requires-Dist: kornia ==0.6.4
Requires-Dist: scikit-image ==0.19.2
Requires-Dist: pytest
Requires-Dist: Pillow
Requires-Dist: facenet-pytorch ==2.5.3
